cartoonart/__init__.py
cartoonart/cli.py
cartoonart/image_processor.py
cartoonart/video_processor.py
cartoonart-1.0.5.dist-info/LICENSE.txt
cartoonart-1.0.5.dist-info/METADATA
cartoonart-1.0.5.dist-info/WHEEL
cartoonart-1.0.5.dist-info/entry_points.txt
cartoonart-1.0.5.dist-info/top_level.txt
cartoonart-1.0.5.dist-info/RECORD
